cchess/__init__.py
cchess/board.py
cchess/exception.py
cchess/game.py
cchess/move.py
cchess/piece.py
cczero/__init__.py
cczero/api.py
cczero/common.py
cczero/env.py
cczero/lookup_tables.py
cczero/mini.py
cczero/model.py
cczero/model_helper.py
cczero/play.py
cczero/player.py
cczero/static_env.py
cczero_engine-0.8.dist-info/METADATA
cczero_engine-0.8.dist-info/WHEEL
cczero_engine-0.8.dist-info/top_level.txt
cczero_engine-0.8.dist-info/RECORD
